docassemble_wrappers/__init__.py
docassemble_wrappers/validator_collection_br.py
docassemble_wrappers-0.0.6.dist-info/LICENSE.txt
docassemble_wrappers-0.0.6.dist-info/METADATA
docassemble_wrappers-0.0.6.dist-info/WHEEL
docassemble_wrappers-0.0.6.dist-info/top_level.txt
docassemble_wrappers-0.0.6.dist-info/RECORD
