Metadata-Version: 2.1
Name: docassemble-wrappers
Version: 0.0.6
Summary: Wrappers to external functionalities and Docassemble API
Home-page: https://github.com/silexsistemas/docassemble-wrappers
Author: Roberto Vasconcelos Novaes, Luiz Guilherme Paim, Iasmini Gomes
Author-email: rnovaes@ufmg.br, luis.paimadv@gmail.com, iasmini@silexsistemas.com.br
License: MIT
Project-URL: Documentation, https://github.com/rvnovaes/docassemble-wrappers
Project-URL: Bug Reports, https://github.com/rvnovaes/docassemble-wrappers/issues
Project-URL: Source, https://github.com/rvnovaes/docassemble-wrappers
Platform: UNKNOWN
Classifier: Development Status :: 3 - Alpha
Classifier: Environment :: Console
Classifier: Operating System :: OS Independent
Classifier: Intended Audience :: Developers
Classifier: Topic :: Software Development :: Libraries
Classifier: Topic :: Utilities
Classifier: Topic :: Software Development :: Libraries :: Python Modules
Classifier: License :: OSI Approved :: MIT License
Classifier: Programming Language :: Python :: 3.6
Requires-Dist: validator-collection-br
